{
    "modulesccd1607": [{
            "component": "CCD-Web-Server",
            "type": "module",
            "working": "yes",
            "timeStamp": "2016-09-28T00:00:00.000Z"
        },
        {
            "component": "WorkFlow Engine",
            "type": "module",
            "working": "yes",
            "timeStamp": "2016-09-28T00:00:00.000Z"
        },
        {
            "component": "A&AI Mediator",
            "type": "module",
            "working": "no",
            "timeStamp": "2016-09-28T00:00:00.000Z"
        },
        {
            "component": "Blueprint generator",
            "type": "module",
            "working": "notsure",
            "timeStamp": "2016-09-28T00:00:00.000Z"
        },
        {
            "component": "MSO-Deployer",
            "type": "module",
            "working": "notsure",
            "timeStamp": "2016-09-28T00:00:00.000Z"
        },
        {
            "component": "uPCE Orchestrator",
            "type": "module",
            "working": "yes",
            "timeStamp": "2016-09-28T00:00:00.000Z"
        },
        {
            "component": "Catalog",
            "type": "module",
            "working": "no",
            "timeStamp": "2016-09-28T00:00:00.000Z"
        },
        {
            "component": "Validator",
            "type": "module",
            "working": "yes",
            "timeStamp": "2016-09-28T00:00:00.000Z"
        },
        {
            "component": "Task-Dispatcher",
            "type": "module",
            "working": "no",
            "timeStamp": "2016-09-28T00:00:00.000Z"
        }
    ]
}